{
    "base_files_url": "",
    "db_files": [],
    "db_id": "favorites",
    "db_url": "https://raw.githubusercontent.com/wizzomafizzo/MiSTer_Favorites/main/favorites.json",
    "default_options": {},
    "files": {
        "Scripts/favorites.sh": {
            "hash": "34a605d3ca1dfeeaa33b40171964a870",
            "size": 35535,
            "url": "https://raw.githubusercontent.com/wizzomafizzo/MiSTer_Favorites/main/favorites.sh"
        }
    },
    "folders": {
        "Scripts": {}
    },
    "timestamp": 1695350483,
    "zips": {}
}